MANIFEST.in
README.rst
requirements.txt
setup.py
test-requirements.txt
bin/route53-transfer
route53_transfer/__init__.py
route53_transfer/app.py
route53_transfer.egg-info/PKG-INFO
route53_transfer.egg-info/SOURCES.txt
route53_transfer.egg-info/dependency_links.txt
route53_transfer.egg-info/requires.txt
route53_transfer.egg-info/top_level.txt