Metadata-Version: 1.0
Name: route53-transfer
Version: 0.1.1
Summary: Backup and restore Route53 zones, or transfer between AWS accounts.
Home-page: http://github.com/RisingOak/route53-transfer
Author: Cosmin Stejerean
Author-email: cosmin@offbytwo.com
License: Apache License 2.0
Platform: UNKNOWN
Classifier: Development Status :: 3 - Alpha
Classifier: Environment :: Console
Classifier: License :: OSI Approved :: Apache Software License
Classifier: Topic :: Utilities
